Metadata-Version: 1.0
Name: wbaran-probability
Version: 1.0
Summary: Gaussian and Binomial distributions
Home-page: UNKNOWN
Author: Wren Baran
Author-email: wren@wabzs.com
License: UNKNOWN
Platform: UNKNOWN
